amazon_product_details_scraper/__init__.py
amazon_product_details_scraper/app.py
amazon_product_details_scraper/config/__init__.py
amazon_product_details_scraper/config/config.py
amazon_product_details_scraper/core/__init__.py
amazon_product_details_scraper/core/scraper.py
amazon_product_details_scraper/core/utils.py
amazon_product_details_scraper-1.0.5.dist-info/LICENSE
amazon_product_details_scraper-1.0.5.dist-info/METADATA
amazon_product_details_scraper-1.0.5.dist-info/WHEEL
amazon_product_details_scraper-1.0.5.dist-info/entry_points.txt
amazon_product_details_scraper-1.0.5.dist-info/top_level.txt
amazon_product_details_scraper-1.0.5.dist-info/RECORD
