Metadata-Version: 2.1
Name: amazon-product-details-scraper
Version: 1.0.5
Summary: Scrapes product details from Amazon product pages and also downloads the images
Home-page: https://github.com/ranjan-mohanty/amazon-product-details-scraper/blob/main/README.md
Author: Ranjan Mohanty
Author-email: ranjan@duck.com
Project-URL: Source, https://github.com/ranjan-mohanty/amazon-product-details-scraper
Keywords: amazon,scraper
License-File: LICENSE
Requires-Dist: requests ==2.32.3
Requires-Dist: beautifulsoup4 ==4.12.3
Requires-Dist: urllib3 ==2.2.2
